param_management_client/__init__.py
param_management_client/client.py
param_management_client/exceptions.py
param_management_client/backend/__init__.py
param_management_client/backend/crud.py
param_management_client/backend/database.py
param_management_client/backend/export_import_test_tool.py
param_management_client/backend/export_utils.py
param_management_client/backend/import_utils.py
param_management_client/backend/main.py
param_management_client/backend/project_compare_tool.py
param_management_client/backend/schemas.py
param_management_client/backend/io_formats/__init__.py
param_management_client/backend/io_formats/registry.py
param_management_client/backend/io_formats/validation.py
param_management_client/backend/io_formats/excel_rich/__init__.py
param_management_client/backend/io_formats/excel_rich/exporter.py
param_management_client/backend/io_formats/excel_rich/importer.py
param_management_client/backend/io_formats/json/__init__.py
param_management_client/backend/io_formats/json/exporter.py
param_management_client/backend/io_formats/json/importer.py
param_management_client/backend/io_formats/text/__init__.py
param_management_client/backend/io_formats/text/exporter.py
param_management_client-2.0.1.dist-info/LICENSE
param_management_client-2.0.1.dist-info/METADATA
param_management_client-2.0.1.dist-info/WHEEL
param_management_client-2.0.1.dist-info/top_level.txt
param_management_client-2.0.1.dist-info/RECORD
