Metadata-Version: 2.1
Name: param-management-client
Version: 2.0.1
Summary: 参数管理系统 Python 客户端，支持类似pandas DataFrame的点号访问方式，内置完整后端服务
Home-page: https://github.com/yourusername/param-management-client
Author: Your Name
Author-email: Your Name <your.email@example.com>
License: MIT
Project-URL: Homepage, https://github.com/yourusername/param-management-client
Project-URL: Documentation, https://github.com/yourusername/param-management-client#readme
Project-URL: Repository, https://github.com/yourusername/param-management-client
Project-URL: Bug Tracker, https://github.com/yourusername/param-management-client/issues
Keywords: parameter,management,optimization,pyomo,pandas-like,dot notation,fastapi,backend,embedded server,database
Classifier: Development Status :: 4 - Beta
Classifier: Intended Audience :: Developers
Classifier: Intended Audience :: Science/Research
Classifier: License :: OSI Approved :: MIT License
Classifier: Operating System :: OS Independent
Classifier: Programming Language :: Python :: 3
Classifier: Programming Language :: Python :: 3.7
Classifier: Programming Language :: Python :: 3.8
Classifier: Programming Language :: Python :: 3.9
Classifier: Programming Language :: Python :: 3.10
Classifier: Programming Language :: Python :: 3.11
Classifier: Topic :: Scientific/Engineering
Classifier: Topic :: Software Development :: Libraries :: Python Modules
Requires-Python: >=3.7
License-File: LICENSE
Requires-Dist: requests >=2.25.0
Requires-Dist: fastapi >=0.104.0
Requires-Dist: uvicorn[standard] >=0.24.0
Requires-Dist: sqlalchemy >=2.0.0
Requires-Dist: pydantic >=2.5.0
Requires-Dist: python-multipart >=0.0.6
Requires-Dist: openpyxl >=3.1.0
Requires-Dist: pandas >=2.1.0
Requires-Dist: reportlab >=4.0.0
Requires-Dist: python-jose[cryptography] >=3.3.0
Requires-Dist: passlib[bcrypt] >=1.7.4
Requires-Dist: python-dotenv >=1.0.0
Provides-Extra: dev
Requires-Dist: pytest >=6.0.0 ; extra == 'dev'
Requires-Dist: pytest-cov >=2.0.0 ; extra == 'dev'
Requires-Dist: black >=21.0.0 ; extra == 'dev'
Requires-Dist: flake8 >=3.8.0 ; extra == 'dev'
Requires-Dist: mypy >=0.800 ; extra == 'dev'
Provides-Extra: pyomo
Requires-Dist: pyomo >=6.0.0 ; extra == 'pyomo'
